Metadata-Version: 2.4
Name: swift-parser-py
Version: 0.5.0
Summary: Python-based metadata-driven parser for SWIFT/ISO 15022 messages with infinite loop prevention and multi-message support
Home-page: https://github.com/solchos/swift-parser
Author: Solchos
Author-email: Solchos <solchos@gmail.com>
License-Expression: MIT
Project-URL: Homepage, https://github.com/solchos/swift-parser
Project-URL: Bug Tracker, https://github.com/solchos/swift-parser/issues
Keywords: swift,iso15022,finance,banking,parser,multi-message,infinite-loop-prevention,timeout-protection,cli
Classifier: Programming Language :: Python :: 3
Classifier: Programming Language :: Python :: 3.8
Classifier: Programming Language :: Python :: 3.9
Classifier: Programming Language :: Python :: 3.10
Classifier: Programming Language :: Python :: 3.11
Classifier: Programming Language :: Python :: 3.12
Classifier: Operating System :: OS Independent
Classifier: Topic :: Office/Business :: Financial
Classifier: Topic :: Software Development :: Libraries :: Python Modules
Requires-Python: >=3.8
License-File: LICENSE
Requires-Dist: typing>=3.7.4
Dynamic: author
Dynamic: home-page
Dynamic: license-file
Dynamic: requires-dist
Dynamic: requires-python
